ladderbot/Logo.ico
ladderbot/Logo.svg
ladderbot/__init__.py
ladderbot/controllers.py
ladderbot/creds.json
ladderbot/gui.py
ladderbot/html_creator.py
ladderbot/items.py
ladderbot/mappings.py
ladderbot/o.js
ladderbot/run.py
ladderbot/vault_equipment.xlsx
resources/update.py
ladderbot-0.0.19.dist-info/LICENSE
ladderbot-0.0.19.dist-info/METADATA
ladderbot-0.0.19.dist-info/WHEEL
ladderbot-0.0.19.dist-info/entry_points.txt
ladderbot-0.0.19.dist-info/top_level.txt
ladderbot-0.0.19.dist-info/RECORD
