Metadata-Version: 2.1
Name: ladderbot
Version: 0.0.19
Summary: game automation
Author-email: ch7cken <ch7cken@proton.me>
Project-URL: Homepage, https://github.com/pypa/sampleproject
Project-URL: Bug Tracker, https://github.com/pypa/sampleproject/issues
Classifier: Programming Language :: Python :: 3
Classifier: License :: OSI Approved :: MIT License
Classifier: Operating System :: OS Independent
Requires-Python: >=3.7
License-File: LICENSE
Requires-Dist: selenium
Requires-Dist: pandas ==2.0.3
Requires-Dist: openpyxl ==3.1.2
